labManager/common/__init__.py
labManager/common/async_thread.py
labManager/common/config.py
labManager/common/counter.py
labManager/common/enum_helper.py
labManager/common/eye_tracker.py
labManager/common/file_actions.py
labManager/common/message.py
labManager/common/secrets.py
labManager/common/share.py
labManager/common/structs.py
labManager/common/task.py
labManager/common/network/__init__.py
labManager/common/network/admin_conn.py
labManager/common/network/comms.py
labManager/common/network/ifs.py
labManager/common/network/keepalive.py
labManager/common/network/ldap.py
labManager/common/network/mdns.py
labManager/common/network/nmb.py
labManager/common/network/smb.py
labManager/common/network/ssdp.py
labManager/common/network/toems.py
labManager/common/network/utils.py
labManager/common/network/wol.py
labmanager_common-1.0.5.dist-info/METADATA
labmanager_common-1.0.5.dist-info/WHEEL
labmanager_common-1.0.5.dist-info/licenses/LICENSE
labmanager_common-1.0.5.dist-info/RECORD
